protFeat/__init__.py
protFeat/feature_extracter.py
protFeat/utils.py
protFeat/POSSUM_Standalone_Toolkit/__init__.py
protFeat/POSSUM_Standalone_Toolkit/src/__init__.py
protFeat/POSSUM_Standalone_Toolkit/src/featureGenerator.py
protFeat/POSSUM_Standalone_Toolkit/src/headerHandler.py
protFeat/POSSUM_Standalone_Toolkit/src/matrixTransformer.py
protFeat/POSSUM_Standalone_Toolkit/src/possum.py
protFeat/POSSUM_Standalone_Toolkit/src/possum_ft.py
protFeat/iFeature/__init__.py
protFeat/iFeature/cluster.py
protFeat/iFeature/feaSelector.py
protFeat/iFeature/iFeature.py
protFeat/iFeature/iFeaturePseKRAAC.py
protFeat/iFeature/PseKRAAC/__init__.py
protFeat/iFeature/PseKRAAC/type1.py
protFeat/iFeature/PseKRAAC/type10.py
protFeat/iFeature/PseKRAAC/type11.py
protFeat/iFeature/PseKRAAC/type12.py
protFeat/iFeature/PseKRAAC/type13.py
protFeat/iFeature/PseKRAAC/type14.py
protFeat/iFeature/PseKRAAC/type15.py
protFeat/iFeature/PseKRAAC/type16.py
protFeat/iFeature/PseKRAAC/type2.py
protFeat/iFeature/PseKRAAC/type3A.py
protFeat/iFeature/PseKRAAC/type3B.py
protFeat/iFeature/PseKRAAC/type4.py
protFeat/iFeature/PseKRAAC/type5.py
protFeat/iFeature/PseKRAAC/type6A.py
protFeat/iFeature/PseKRAAC/type6B.py
protFeat/iFeature/PseKRAAC/type6C.py
protFeat/iFeature/PseKRAAC/type7.py
protFeat/iFeature/PseKRAAC/type8.py
protFeat/iFeature/PseKRAAC/type9.py
protFeat/iFeature/clusters/__init__.py
protFeat/iFeature/clusters/apc.py
protFeat/iFeature/clusters/dbscan.py
protFeat/iFeature/clusters/hcluster.py
protFeat/iFeature/clusters/kmeans.py
protFeat/iFeature/clusters/meanshift.py
protFeat/iFeature/clusters/pca.py
protFeat/iFeature/clusters/readCode.py
protFeat/iFeature/clusters/saveCluster.py
protFeat/iFeature/clusters/tsne.py
protFeat/iFeature/codes/AAC.py
protFeat/iFeature/codes/AAINDEX.py
protFeat/iFeature/codes/APAAC.py
protFeat/iFeature/codes/ASA.py
protFeat/iFeature/codes/BINARY.py
protFeat/iFeature/codes/BLOSUM62.py
protFeat/iFeature/codes/CKSAAGP.py
protFeat/iFeature/codes/CKSAAP.py
protFeat-1.1.dist-info/LICENSE
protFeat-1.1.dist-info/METADATA
protFeat-1.1.dist-info/WHEEL
protFeat-1.1.dist-info/top_level.txt
protFeat-1.1.dist-info/RECORD
